evaluation_client/README.md
evaluation_client/__init__.py
evaluation_client/assets.py
evaluation_client/config.py
evaluation_client/evaluation_client.py
evaluation_client/monitoring.py
evaluation_client/options.py
evaluation_client/py.typed
evaluation_client/suite.py
evaluation_client/sdk/__init__.py
evaluation_client/sdk/artifacts.py
evaluation_client/sdk/http.py
evaluation_client/sdk/models.py
evaluation_client/sdk/runs.py
evaluation_client/sdk/streaming.py
evaluation_client-0.1.0.dist-info/METADATA
evaluation_client-0.1.0.dist-info/WHEEL
evaluation_client-0.1.0.dist-info/RECORD
