Metadata-Version: 2.4
Name: evaluation-client
Version: 0.1.0
Summary: Python SDK for interacting with the Chatbot Evaluation API.
Author-email: habib-z <habib.zafarian@gmail.com>
License: Proprietary
Keywords: chatbot,evaluation,sdk
Classifier: Intended Audience :: Developers
Classifier: License :: Other/Proprietary License
Classifier: Programming Language :: Python :: 3
Classifier: Programming Language :: Python :: 3.10
Classifier: Programming Language :: Python :: 3.11
Classifier: Programming Language :: Python :: 3.12
Classifier: Typing :: Typed
Requires-Python: <3.13.0,>=3.10
Requires-Dist: chatbot-eval-common<0.2,>=0.1.0
Requires-Dist: pydantic<3.0,>=2.6
Requires-Dist: requests<3.0,>=2.32
Requires-Dist: rich>=14.2.0
